paper_per_year/__init__.py
paper_per_year/cli.py
paper_per_year/core.py
paper_per_year-0.2.0.dist-info/METADATA
paper_per_year-0.2.0.dist-info/WHEEL
paper_per_year-0.2.0.dist-info/entry_points.txt
paper_per_year-0.2.0.dist-info/RECORD
