Metadata-Version: 2.4
Name: paper-per-year
Version: 0.2.0
Summary: Generate publication per year plots for academic authors
Project-URL: Homepage, https://github.com/dwahdany/paper-per-year
Project-URL: Repository, https://github.com/dwahdany/paper-per-year.git
Author-email: Dariush Wahdany <dariushwahdany@gmail.com>
License: CC-BY-SA-4.0
Keywords: publications,scholar,visualization
Classifier: Development Status :: 4 - Beta
Classifier: Environment :: Console
Classifier: Intended Audience :: Science/Research
Classifier: License :: OSI Approved :: MIT License
Classifier: Programming Language :: Python :: 3
Classifier: Topic :: Scientific/Engineering :: Visualization
Requires-Python: >=3.13
Requires-Dist: click>=8.1.7
Requires-Dist: matplotlib>=3.7.0
Requires-Dist: numpy>=1.24.0
Requires-Dist: scholarly>=1.7.11
Requires-Dist: seaborn>=0.13.2
